odoo8_addon_sale_automatic_workflow_exception-8.0.1.0.0.99.dev3-py2.7-nspkg.pth
odoo8_addon_sale_automatic_workflow_exception-8.0.1.0.0.99.dev3.dist-info/METADATA
odoo8_addon_sale_automatic_workflow_exception-8.0.1.0.0.99.dev3.dist-info/RECORD
odoo8_addon_sale_automatic_workflow_exception-8.0.1.0.0.99.dev3.dist-info/WHEEL
odoo8_addon_sale_automatic_workflow_exception-8.0.1.0.0.99.dev3.dist-info/namespace_packages.txt
odoo8_addon_sale_automatic_workflow_exception-8.0.1.0.0.99.dev3.dist-info/top_level.txt
odoo_addons/sale_automatic_workflow_exception/README.rst
odoo_addons/sale_automatic_workflow_exception/__init__.py
odoo_addons/sale_automatic_workflow_exception/__openerp__.py
odoo_addons/sale_automatic_workflow_exception/automatic_workflow_job.py
odoo_addons/sale_automatic_workflow_exception/i18n/sale_automatic_workflow_exception.pot
odoo_addons/sale_automatic_workflow_exception/static/description/icon.png
